timediffz/__init__.py
timediffz/timediffz.py
timediffz-1.0.5.dist-info/METADATA
timediffz-1.0.5.dist-info/WHEEL
timediffz-1.0.5.dist-info/licenses/LICENSE
timediffz-1.0.5.dist-info/RECORD
