Metadata-Version: 2.4
Name: timediffz
Version: 1.0.5
Summary: a library for advanced and accurate timestamping and time differences
Project-URL: Homepage, https://github.com/WeDu-official/timediffz
Project-URL: Issues, https://github.com/WeDu-official/timediffz/issues
Author-email: WeDu-official <fplu.the.founder@gmail.com>
License-File: LICENSE
Classifier: Development Status :: 5 - Production/Stable
Classifier: Intended Audience :: Developers
Classifier: Intended Audience :: Science/Research
Classifier: License :: OSI Approved :: MIT License
Classifier: Natural Language :: English
Classifier: Operating System :: POSIX :: Linux
Classifier: Programming Language :: Python :: 3.10
Classifier: Programming Language :: Python :: 3.11
Classifier: Programming Language :: Python :: 3.12
Classifier: Programming Language :: Python :: 3.13
Classifier: Programming Language :: Python :: Implementation
Classifier: Programming Language :: Python :: Implementation :: CPython
Classifier: Topic :: Internet
Requires-Python: >=3.10
Requires-Dist: cython==3.2.2
Requires-Dist: requests==2.32.5
Requires-Dist: setuptools==80.9.0
Requires-Dist: td1inner==1.0.6
Requires-Dist: td2inner==1.0.6
